[       {
            "url": "images/Beauty/42.jpg",
            "thumbUrl": "images/Beauty/Thumbernail/42_120x175.jpg",
            "height": "150px",
            "width": "150px"
        },
        {
            "url": "images/Beauty/43.jpg",
            "thumbUrl": "images/Beauty/Thumbernail/43_120x175.jpg",
            "height": "150px",
            "width": "150px"
        },
        {
            "url": "images/Beauty/37.jpg",
            "thumbUrl": "images/Beauty/Thumbernail/37_120x175.jpg",
            "height": "150px",
            "width": "150px"
        },
      {
            "url": "images/Beauty/38.jpg",
            "thumbUrl": "images/Beauty/Thumbernail/38_120x175.jpg",
            "height": "150px",
            "width": "150px"
        },
        {
            "url": "images/Beauty/39.jpg",
            "thumbUrl": "images/Beauty/Thumbernail/39_120x175.jpg",
            "height": "150px",
            "width": "150px"
        },
        {
            "url": "images/Beauty/40.jpg",
            "thumbUrl": "images/Beauty/Thumbernail/40_120x175.jpg",
            "height": "150px",
            "width": "150px"
        },
        {
            "url": "images/Beauty/41.jpg",
            "thumbUrl": "images/Beauty/Thumbernail/41_120x175.jpg",
            "height": "150px",
            "width": "150px"
        },
        {
            "url": "images/Beauty/1.jpg",
            "thumbUrl": "images/Beauty/Thumbernail/1_120x175.jpg",
            "height": "150px",
            "width": "150px"
        },
        {
            "url": "images/Beauty/2.jpg",
            "thumbUrl": "images/Beauty/Thumbernail/2_120x175.jpg",
            "height": "150px",
            "width": "150px"
        },
        {
            "url": "images/Beauty/3.jpg",
            "thumbUrl": "images/Beauty/Thumbernail/3_120x175.jpg",
            "height": "150px",
            "width": "150px"
        },
        {
            "url": "images/Beauty/4.jpg",
            "thumbUrl": "images/Beauty/Thumbernail/4_120x175.jpg",
            "height": "150px",
            "width": "150px"
        },
        {
            "url": "images/Beauty/5.jpg",
            "thumbUrl": "images/Beauty/Thumbernail/5_120x175.jpg",
            "height": "150px",
            "width": "150px"
        },
        {
            "url": "images/Beauty/6.jpg",
            "thumbUrl": "images/Beauty/Thumbernail/6_120x175.jpg",
            "height": "150px",
            "width": "150px"
        },
        {
            "url": "images/Beauty/7.jpg",
            "thumbUrl": "images/Beauty/Thumbernail/7_120x175.jpg",
            "height": "150px",
            "width": "150px"
        },
        {
            "url": "images/Beauty/8.JPG",
            "thumbUrl": "images/Beauty/Thumbernail/8_120x175.jpg",
            "height": "150px",
            "width": "150px"
        },
        {
            "url": "images/Beauty/9.jpg",
            "thumbUrl": "images/Beauty/Thumbernail/9_120x175.jpg",
            "height": "150px",
            "width": "150px"
        },
        {
            "url": "images/Beauty/10.jpg",
            "thumbUrl": "images/Beauty/Thumbernail/10_120x175.jpg",
            "height": "150px",
            "width": "150px"
        },
        {
            "url": "images/Beauty/11.jpg",
            "thumbUrl": "images/Beauty/Thumbernail/11_120x175.jpg",
            "height": "150px",
            "width": "150px"
        },
        {
            "url": "images/Beauty/12.jpg",
            "thumbUrl": "images/Beauty/Thumbernail/12_120x175.jpg",
            "height": "150px",
            "width": "150px"
        },
        {
            "url": "images/Beauty/14.jpg",
            "thumbUrl": "images/Beauty/Thumbernail/14_120x175.jpg",
            "height": "150px",
            "width": "150px"
        },
        {
            "url": "images/Beauty/15.jpg",
            "thumbUrl": "images/Beauty/Thumbernail/15_120x175.jpg",
            "height": "150px",
            "width": "150px"
        },
        {
            "url": "images/Beauty/16.JPG",
            "thumbUrl": "images/Beauty/Thumbernail/16_120x175.jpg",
            "height": "150px",
            "width": "150px"
        },
        {
            "url": "images/Beauty/17.JPG",
            "thumbUrl": "images/Beauty/Thumbernail/17_120x175.jpg",
            "height": "150px",
            "width": "150px"
        },
        {
            "url": "images/Beauty/18.JPG",
            "thumbUrl": "images/Beauty/Thumbernail/18_120x175.jpg",
            "height": "150px",
            "width": "150px"
        },
          {
            "url": "images/Beauty/19.jpg",
            "thumbUrl": "images/Beauty/Thumbernail/19_240x175.jpg",
            "height": "150px",
            "width": "150px"
        },
        {
            "url": "images/Beauty/20.jpg",
            "thumbUrl": "images/Beauty/Thumbernail/20_120x175.jpg",
            "height": "150px",
            "width": "150px"
        },
        {
            "url": "images/Beauty/21.jpg",
            "thumbUrl": "images/Beauty/Thumbernail/21_120x175.jpg",
            "height": "150px",
            "width": "150px"
        },
        {
            "url": "images/Beauty/22.jpg",
            "thumbUrl": "images/Beauty/Thumbernail/22_120x175.jpg",
            "height": "150px",
            "width": "150px"
        },
        {
            "url": "images/Beauty/23.jpg",
            "thumbUrl": "images/Beauty/Thumbernail/23_120x175.jpg",
            "height": "150px",
            "width": "150px"
        },
        {
            "url": "images/Beauty/24.jpg",
            "thumbUrl": "images/Beauty/Thumbernail/24_120x175.jpg",
            "height": "150px",
            "width": "150px"
        },
        {
            "url": "images/Beauty/25.jpg",
            "thumbUrl": "images/Beauty/Thumbernail/25_240x175.jpg",
            "height": "150px",
            "width": "150px"
        },
        {
            "url": "images/Beauty/26.jpg",
            "thumbUrl": "images/Beauty/Thumbernail/26_120x175.jpg",
            "height": "150px",
            "width": "150px"
        },
        {
            "url": "images/Beauty/27.JPG",
            "thumbUrl": "images/Beauty/Thumbernail/27_120x175.jpg",
            "height": "150px",
            "width": "150px"
        },
        {
            "url": "images/Beauty/28.JPG",
            "thumbUrl": "images/Beauty/Thumbernail/28_120x175.jpg",
            "height": "150px",
            "width": "150px"
        },
        {
            "url": "images/Beauty/29.jpg",
            "thumbUrl": "images/Beauty/Thumbernail/29_120x175.jpg",
            "height": "150px",
            "width": "150px"
        },
        {
            "url": "images/Beauty/30.jpg",
            "thumbUrl": "images/Beauty/Thumbernail/30_120x175.jpg",
            "height": "150px",
            "width": "150px"
        },
        {
            "url": "images/Beauty/31.jpg",
            "thumbUrl": "images/Beauty/Thumbernail/31_120x175.jpg",
            "height": "150px",
            "width": "150px"
        },
        {
            "url": "images/Beauty/32.jpg",
            "thumbUrl": "images/Beauty/Thumbernail/32_120x175.jpg",
            "height": "150px",
            "width": "150px"
        },
        {
            "url": "images/Beauty/33.JPG",
            "thumbUrl": "images/Beauty/Thumbernail/33_120x175.jpg",
            "height": "150px",
            "width": "150px"
        },
        {
            "url": "images/Beauty/34.jpg",
            "thumbUrl": "images/Beauty/Thumbernail/34_120x175.jpg",
            "height": "150px",
            "width": "150px"
        },
        {
            "url": "images/Beauty/35.jpg",
            "thumbUrl": "images/Beauty/Thumbernail/35_120x175.jpg",
            "height": "150px",
            "width": "150px"
        },
        {
            "url": "images/Beauty/36.JPG",
            "thumbUrl": "images/Beauty/Thumbernail/36_120x175.jpg",
            "height": "150px",
            "width": "150px"
        }

]
